decisify/__init__.py
decisify/core.py
decisify/explainer.py
decisify/optimizer.py
decisify/utils.py
decisify-0.1.0.dist-info/METADATA
decisify-0.1.0.dist-info/WHEEL
decisify-0.1.0.dist-info/licenses/LICENSE.md
decisify-0.1.0.dist-info/RECORD
