Metadata-Version: 2.3
Name: decisify
Version: 0.1.0
Summary: Add your description here
Author-email: Sharabh Shukla <shuklasharabh@gmail.com>
Requires-Python: >=3.10
Requires-Dist: crewai>=0.80.0
Requires-Dist: gurobipy>=12.0.0
Requires-Dist: magentic>=0.32.0
Requires-Dist: modelsmith>=0.6.1
Requires-Dist: pydantic>=2.10.1
